Metadata-Version: 2.1
Name: CogentDataHubAPI
Version: 0.1.2
Summary: Python API for real-time data access to Cogent DataHub
Home-page: https://github.com/cogentrts/DataHubPythonAPI
Download-URL: https://github.com/cogentrts/DataHubPythonAPI/archive/refs/tags/v0.1.2.tar.gz
Author: Colin Yuen
Author-email: colin.yuen@skkynet.com
License: MIT
Keywords: Cogent,DataHub,Api,Python
Classifier: Development Status :: 4 - Beta
Classifier: Intended Audience :: Developers
Classifier: Topic :: Software Development :: Build Tools
Classifier: License :: OSI Approved :: MIT License
Classifier: Programming Language :: Python :: 3
Classifier: Programming Language :: Python :: 3.7
Classifier: Programming Language :: Python :: 3.8
Classifier: Programming Language :: Python :: 3.9
Classifier: Programming Language :: Python :: 3.10
Classifier: Programming Language :: Python :: 3.11
Classifier: Programming Language :: Python :: 3.12
License-File: LICENSE.txt
